PufferRelay/__init__.py
PufferRelay/__main__.py
PufferRelay/config.py
PufferRelay/core_imports.py
PufferRelay/logger.py
PufferRelay/database/__init__.py
PufferRelay/database/db_connector.py
PufferRelay/database/db_models.py
PufferRelay/database/db_queries.py
PufferRelay/database/db_version.py
PufferRelay/pcap_processing/__init__.py
PufferRelay/pcap_processing/pcap_parser.py
PufferRelay/protocols/__init__.py
PufferRelay/protocols/ftp_handler.py
PufferRelay/protocols/http_handler.py
PufferRelay/protocols/imap_handler.py
PufferRelay/protocols/ip_handler.py
PufferRelay/protocols/ldap_handler.py
PufferRelay/protocols/netbios_handler.py
PufferRelay/protocols/ntlm_handler.py
PufferRelay/protocols/pop3_handler.py
PufferRelay/protocols/smtp_handler.py
PufferRelay/protocols/telnet_handler.py
PufferRelay/tests/test_db_connector.py
PufferRelay/tests/test_ftp_handler.py
PufferRelay/tests/test_general_handler.py
PufferRelay/tests/test_http_handler.py
PufferRelay/tests/test_ldap_handler.py
PufferRelay/tests/test_pcap_parser.py
PufferRelay/tests/test_smtp_handler.py
PufferRelay/tests/test_telnet_handler.py
PufferRelay/utils/__init__.py
PufferRelay/utils/display.py
PufferRelay/utils/helpers.py
PufferRelay/utils/loading_animation.py
PufferRelay/utils/logger.py
pufferrelay-1.0.7.dist-info/licenses/LICENSE
pufferrelay-1.0.7.dist-info/licenses/NOTICE
pufferrelay-1.0.7.dist-info/METADATA
pufferrelay-1.0.7.dist-info/WHEEL
pufferrelay-1.0.7.dist-info/entry_points.txt
pufferrelay-1.0.7.dist-info/top_level.txt
pufferrelay-1.0.7.dist-info/RECORD
