Metadata-Version: 2.4
Name: pufferrelay
Version: 1.0.7
Summary: A network protocol analyzer and credential extractor
Author-email: Massamba DIOUF <your.email@example.com>
License-Expression: GPL-3.0-or-later
Project-URL: Homepage, https://github.com/mpolymath/PufferRelay
Project-URL: Repository, https://github.com/mpolymath/PufferRelay.git
Project-URL: Documentation, https://github.com/mpolymath/PufferRelay#readme
Classifier: Development Status :: 4 - Beta
Classifier: Intended Audience :: System Administrators
Classifier: Programming Language :: Python :: 3
Classifier: Programming Language :: Python :: 3.8
Classifier: Programming Language :: Python :: 3.9
Classifier: Programming Language :: Python :: 3.10
Classifier: Programming Language :: Python :: 3.11
Classifier: Topic :: Security
Classifier: Topic :: System :: Networking :: Monitoring
Requires-Python: >=3.8
License-File: LICENSE
License-File: NOTICE
Requires-Dist: pyshark>=0.6
Requires-Dist: python-dotenv>=1.1.0
Requires-Dist: rich>=14.0.0
Provides-Extra: dev
Requires-Dist: pytest>=6.0; extra == "dev"
Requires-Dist: black>=22.0; extra == "dev"
Requires-Dist: flake8>=4.0; extra == "dev"
Requires-Dist: mypy>=0.900; extra == "dev"
Dynamic: license-file
